Metadata-Version: 2.1
Name: full_fred
Version: 0.0.9a3
Summary: Full interface to Federal Reserve Economic Data (FRED)
Home-page: https://github.com/7astro7/full_fred
Author: Zachary A. Kraehling
Author-email: zaknyy@protonmail.com
License: UNKNOWN
Project-URL: Tracker, https://github.com/7astro7/full_fred/issues
Project-URL: Source, https://github.com/7astro7/full_fred
Keywords: economics,API,econ,fred,financial,FRED
Platform: Any
Classifier: License :: OSI Approved :: GNU General Public License v3 (GPLv3)
Classifier: Development Status :: 3 - Alpha
Classifier: Intended Audience :: Science/Research
Classifier: Intended Audience :: Developers
Classifier: Intended Audience :: Financial and Insurance Industry
Classifier: Operating System :: OS Independent
Classifier: Topic :: Software Development :: Libraries :: Python Modules
Classifier: Topic :: Internet :: WWW/HTTP
Classifier: Programming Language :: Python :: 3
License-File: LICENSE
